CHANGES.txt
LICENSE.txt
setup.cfg
setup.py
zgeo.kml-configure.zcml
zgeo/__init__.py
zgeo.kml.egg-info/PKG-INFO
zgeo.kml.egg-info/SOURCES.txt
zgeo.kml.egg-info/dependency_links.txt
zgeo.kml.egg-info/entry_points.txt
zgeo.kml.egg-info/namespace_packages.txt
zgeo.kml.egg-info/not-zip-safe
zgeo.kml.egg-info/requires.txt
zgeo.kml.egg-info/top_level.txt
zgeo/kml/README.txt
zgeo/kml/__init__.py
zgeo/kml/browser.py
zgeo/kml/configure.zcml
zgeo/kml/ftesting.zcml
zgeo/kml/interfaces.py
zgeo/kml/kml-docs.txt
zgeo/kml/kml_document.pt
zgeo/kml/testing.py
zgeo/kml/tests.py
zgeo/kml/zope2.py
