Metadata-Version: 1.0
Name: zgeo.kml
Version: 0.4
Summary: Google Earth KML for Zope
Home-page: http://trac.gispython.org/projects/PrimaGIS/wiki/zgeo.kml
Author: Sean Gillies
Author-email: sgillies@frii.com
License: BSD
Keywords: gis geography geospatial kml google earth
Platform: UNKNOWN
Classifier: Framework :: Plone
Classifier: Framework :: Zope3
Classifier: Programming Language :: Python
Classifier: Topic :: Software Development :: Libraries :: Python Modules
Classifier: Topic :: Scientific/Engineering :: GIS
Classifier: Development Status :: 3 - Alpha
Classifier: Intended Audience :: Developers
Classifier: License :: OSI Approved :: BSD License
